bits/__init__.py
bits/secrets/__init__.py
bits_secrets-2.0.0.dist-info/METADATA
bits_secrets-2.0.0.dist-info/WHEEL
bits_secrets-2.0.0.dist-info/RECORD
