Metadata-Version: 2.4
Name: bits-secrets
Version: 2.0.0
Summary: BITS Secrets
License-Expression: BSD-3-Clause
Keywords: bits,google,secrets
Author: Dev Null
Author-email: <devnull@broadinstitute.org>
Requires-Python: >=3.9
Classifier: Programming Language :: Python :: 3
Classifier: Programming Language :: Python :: 3.9
Classifier: Programming Language :: Python :: 3.10
Classifier: Programming Language :: Python :: 3.11
Classifier: Programming Language :: Python :: 3.12
Classifier: Programming Language :: Python :: 3.13
Classifier: Programming Language :: Python :: 3.14
Requires-Dist: google-cloud-secret-manager (>=2.24.0,<3.0.0)
Project-URL: Homepage, https://github.com/broadinstitute/bits-secrets.git
Project-URL: Repository, https://github.com/broadinstitute/bits-secrets.git
